MANIFEST.in
README.txt
setup.py
docs/HISTORY.txt
docs/INSTALL.txt
docs/LICENSE.GPL
docs/LICENSE.txt
medialog/__init__.py
medialog.tinymceplugins.imagestyles.egg-info/PKG-INFO
medialog.tinymceplugins.imagestyles.egg-info/SOURCES.txt
medialog.tinymceplugins.imagestyles.egg-info/dependency_links.txt
medialog.tinymceplugins.imagestyles.egg-info/entry_points.txt
medialog.tinymceplugins.imagestyles.egg-info/namespace_packages.txt
medialog.tinymceplugins.imagestyles.egg-info/not-zip-safe
medialog.tinymceplugins.imagestyles.egg-info/requires.txt
medialog.tinymceplugins.imagestyles.egg-info/top_level.txt
medialog/tinymceplugins/__init__.py
medialog/tinymceplugins/imagestyles/__init__.py
medialog/tinymceplugins/imagestyles/configure.zcml
medialog/tinymceplugins/imagestyles/profiles/default/cssregistry.xml
medialog/tinymceplugins/imagestyles/profiles/default/metadata.xml
medialog/tinymceplugins/imagestyles/profiles/default/skins.xml
medialog/tinymceplugins/imagestyles/profiles/default/tinymce.xml
medialog/tinymceplugins/imagestyles/skins/tinymce_plugin_imagestyles/imagestyles/dialog.htm.pt
medialog/tinymceplugins/imagestyles/skins/tinymce_plugin_imagestyles/imagestyles/editor_plugin.js
medialog/tinymceplugins/imagestyles/skins/tinymce_plugin_imagestyles/imagestyles/css/imagestyle.css
medialog/tinymceplugins/imagestyles/skins/tinymce_plugin_imagestyles/imagestyles/css/imagestyles.css.dtml
medialog/tinymceplugins/imagestyles/skins/tinymce_plugin_imagestyles/imagestyles/css/medialog-imagestyles.css
medialog/tinymceplugins/imagestyles/skins/tinymce_plugin_imagestyles/imagestyles/img/imagestyles.gif
medialog/tinymceplugins/imagestyles/skins/tinymce_plugin_imagestyles/imagestyles/js/dialog.js
medialog/tinymceplugins/imagestyles/skins/tinymce_plugin_imagestyles/imagestyles/langs/en.js
medialog/tinymceplugins/imagestyles/skins/tinymce_plugin_imagestyles/imagestyles/langs/en_dlg.js