Metadata-Version: 1.0
Name: medialog.tinymceplugins.imagestyles
Version: 0.2
Summary: A TinyMCE plugin for having more styles (classes) for images
Home-page: http://svn.plone.org/svn/collective/medialog.tinymceplugins.imagestyles/
Author: Espen Moe-Nilssen
Author-email: espen@medialog.no
License: GPL
Keywords: tinymce plugin image styles
Platform: UNKNOWN
Classifier: Development Status :: 3 - Alpha
Classifier: Framework :: Plone
Classifier: Programming Language :: Python
Classifier: Programming Language :: JavaScript
